[
  {
    "package": "IMD"
  },
  {
    "package": "SBC"
  },
  {
    "package": "adbcbigquery"
  },
  {
    "package": "adbcdrivermanager"
  },
  {
    "package": "adbcflightsql"
  },
  {
    "package": "adbcsnowflake"
  },
  {
    "package": "arrow"
  },
  {
    "package": "asylum"
  },
  {
    "package": "audio.vadwebrtc"
  },
  {
    "package": "audio.whisper"
  },
  {
    "package": "autometric"
  },
  {
    "package": "bridgestan"
  },
  {
    "package": "cmdstanr"
  },
  {
    "package": "crew"
  },
  {
    "package": "crew.aws.batch"
  },
  {
    "package": "crew.cluster"
  },
  {
    "package": "demographr"
  },
  {
    "package": "duckdb"
  },
  {
    "package": "geographr"
  },
  {
    "package": "glaredb"
  },
  {
    "package": "healthyr"
  },
  {
    "package": "httpgd"
  },
  {
    "package": "ichimoku"
  },
  {
    "package": "igraph"
  },
  {
    "package": "jagstargets"
  },
  {
    "package": "later"
  },
  {
    "package": "litedown"
  },
  {
    "package": "loneliness"
  },
  {
    "package": "milRex"
  },
  {
    "package": "mirai"
  },
  {
    "package": "multitools"
  },
  {
    "package": "multiverse.internals"
  },
  {
    "package": "nanoarrow"
  },
  {
    "package": "nanonext"
  },
  {
    "package": "polars"
  },
  {
    "package": "prophet"
  },
  {
    "package": "prqlr"
  },
  {
    "package": "rJavaEnv"
  },
  {
    "package": "rlang"
  },
  {
    "package": "rwasm"
  },
  {
    "package": "stantargets"
  },
  {
    "package": "string2path"
  },
  {
    "package": "tarchetypes"
  },
  {
    "package": "targets"
  },
  {
    "package": "targetsketch"
  },
  {
    "package": "taxizedb"
  },
  {
    "package": "tidypolars"
  },
  {
    "package": "tidytensor"
  },
  {
    "package": "unigd"
  },
  {
    "package": "webchem"
  },
  {
    "package": "webseq"
  },
  {
    "package": "wildfires"
  },
  {
    "package": "zstdlite"
  }
]
