{
  "adbcbigquery": {
    "success": [true],
    "published": ["2025-08-06 07:07:02.755 UTC"],
    "version": ["0.19.0"],
    "remote_hash": ["c18f54a033651ed435c28161f1beaf062eca0720"]
  },
  "adbcdrivermanager": {
    "success": [true],
    "published": ["2025-08-06 06:52:43.138 UTC"],
    "version": ["0.19.0"],
    "remote_hash": ["c18f54a033651ed435c28161f1beaf062eca0720"]
  },
  "adbcflightsql": {
    "success": [true],
    "published": ["2025-08-06 07:06:27.849 UTC"],
    "version": ["0.19.0"],
    "remote_hash": ["c18f54a033651ed435c28161f1beaf062eca0720"]
  },
  "adbcsnowflake": {
    "success": [true],
    "published": ["2025-08-06 07:11:31.763 UTC"],
    "version": ["0.19.0"],
    "remote_hash": ["c18f54a033651ed435c28161f1beaf062eca0720"]
  },
  "arrow": {
    "success": [true],
    "published": ["2025-08-16 07:34:07.213 UTC"],
    "version": ["21.0.0"],
    "remote_hash": ["ee4d09ebef61c663c1efbfa4c18e518a03b798be"]
  },
  "asylum": {
    "success": [false],
    "published": ["2025-08-25 05:53:58.845 UTC"],
    "version": ["1.1.1"],
    "remote_hash": ["22064dd0822e007ef78cd29e9a118beb09e76da4"],
    "cran": ["1.1.2"]
  },
  "audio.vadwebrtc": {
    "success": [true],
    "published": ["2025-08-31 04:15:55.963 UTC"],
    "version": ["0.2"],
    "remote_hash": ["c3de76ddc738dbb4a80ac7ec67ac9da3cba093ba"]
  },
  "audio.whisper": {
    "success": [false],
    "published": ["2025-08-06 05:40:20.048 UTC"],
    "version": ["0.4.1"],
    "remote_hash": ["4b5c6a288c0f46a4cdc47f50d2d35395d3e32194"],
    "r_cmd_check": [
      {
        "check": "WARNING",
        "config": "linux-release-arm64",
        "r": "4.5.1",
        "url": "https://github.com/r-universe/r-multiverse/actions/runs/16768359571/job/47478155591"
      },
      {
        "check": "WARNING",
        "config": "linux-release-x86_64",
        "r": "4.5.1",
        "url": "https://github.com/r-universe/r-multiverse/actions/runs/16768359571/job/47478155592"
      },
      {
        "check": "WARNING",
        "config": "macos-release-arm64",
        "r": "4.5.1",
        "url": "https://github.com/r-universe/r-multiverse/actions/runs/16768359571/job/47478155599"
      },
      {
        "check": "WARNING",
        "config": "macos-release-x86_64",
        "r": "4.5.1",
        "url": "https://github.com/r-universe/r-multiverse/actions/runs/16768359571/job/47478155590"
      },
      {
        "check": "WARNING",
        "config": "windows-release",
        "r": "4.5.1",
        "url": "https://github.com/r-universe/r-multiverse/actions/runs/16768359571/job/47478155633"
      }
    ],
    "remotes": ["bnosac/audio.vadwebrtc"]
  },
  "autometric": {
    "success": [true],
    "published": ["2025-08-09 04:40:06.836 UTC"],
    "version": ["0.1.2"],
    "remote_hash": ["36e98ae76feb34de0783d6505f7f2a17e972fe23"]
  },
  "bridgestan": {
    "success": [false],
    "published": ["2025-08-26 05:43:31.463 UTC"],
    "version": ["2.6.2"],
    "remote_hash": ["2fc25219645f7b465efdd66bbd8f7d9ceaa47cb1"],
    "r_cmd_check": [
      {
        "check": "ERROR",
        "config": "linux-release-x86_64",
        "r": "4.5.1",
        "url": "https://github.com/r-universe/r-multiverse/actions/runs/17229001188/job/48879162554"
      },
      {
        "check": "ERROR",
        "config": "macos-release-arm64",
        "r": "4.5.1",
        "url": "https://github.com/r-universe/r-multiverse/actions/runs/17229001188/job/48879162555"
      },
      {
        "check": "ERROR",
        "config": "windows-release",
        "r": "4.5.1",
        "url": "https://github.com/r-universe/r-multiverse/actions/runs/17229001188/job/48879162516"
      }
    ]
  },
  "cmdstanr": {
    "success": [true],
    "published": ["2025-08-20 03:35:48.358 UTC"],
    "version": ["0.9.0"],
    "remote_hash": ["da99e2ba954658bdad63bffb738c4444c33a4e0e"]
  },
  "colorout": {
    "success": [false],
    "published": ["2025-08-31 06:37:26.757 UTC"],
    "version": ["1.3-3"],
    "remote_hash": ["15ff0be4a3fced8504c1d7ff1d05a64b32bab552"],
    "r_cmd_check": [
      {
        "check": "WARNING",
        "config": "macos-release-arm64",
        "r": "4.5.1",
        "url": "https://github.com/r-universe/r-multiverse/actions/runs/17353544095/job/49263454882"
      },
      {
        "check": "WARNING",
        "config": "macos-release-x86_64",
        "r": "4.5.1",
        "url": "https://github.com/r-universe/r-multiverse/actions/runs/17353544095/job/49263454875"
      }
    ]
  },
  "crew": {
    "success": [true],
    "published": ["2025-08-27 09:41:41.832 UTC"],
    "version": ["1.2.1"],
    "remote_hash": ["c03b80222289c9c94b096f4883d9121ffb8673ca"]
  },
  "crew.aws.batch": {
    "success": [true],
    "published": ["2025-08-16 05:23:01.943 UTC"],
    "version": ["0.0.12"],
    "remote_hash": ["51370ab9e1d1c11a0ee1be0c91a67bbad8db78d3"]
  },
  "crew.cluster": {
    "success": [true],
    "published": ["2025-08-08 07:18:52.286 UTC"],
    "version": ["0.3.8"],
    "remote_hash": ["f5bb1d39d60f5b6204f4b1ca3090f2b11a5246b9"]
  },
  "demographr": {
    "success": [false],
    "published": ["2025-08-03 06:14:04.249 UTC"],
    "version": ["0.0.1"],
    "remote_hash": ["5d73b83f4bd70048d39b6b9c4bffaf02c8aab321"],
    "r_cmd_check": [
      {
        "check": "WARNING",
        "config": "linux-release-x86_64",
        "r": "4.5.1",
        "url": "https://github.com/r-universe/r-multiverse/actions/runs/16701852122/job/47274214102"
      },
      {
        "check": "WARNING",
        "config": "macos-release-arm64",
        "r": "4.5.1",
        "url": "https://github.com/r-universe/r-multiverse/actions/runs/16701852122/job/47274214109"
      },
      {
        "check": "WARNING",
        "config": "windows-release",
        "r": "4.5.1",
        "url": "https://github.com/r-universe/r-multiverse/actions/runs/16701852122/job/47274214131"
      }
    ]
  },
  "duckdb": {
    "success": [true],
    "published": ["2025-08-10 04:30:31.528 UTC"],
    "version": ["1.3.2"],
    "remote_hash": ["76b95a4536054187cb3605da248f94fe5f4383a2"]
  },
  "geographr": {
    "success": [false],
    "published": ["2025-08-09 04:24:29.946 UTC"],
    "version": ["1.0.1"],
    "remote_hash": ["ed416a6735f7c4d8da0b866260369e84c27319a2"],
    "r_cmd_check": [
      {
        "check": "WARNING",
        "config": "linux-release-x86_64",
        "r": "4.5.1",
        "url": "https://github.com/r-universe/r-multiverse/actions/runs/16845307506/job/47724057617"
      },
      {
        "check": "WARNING",
        "config": "macos-release-arm64",
        "r": "4.5.1",
        "url": "https://github.com/r-universe/r-multiverse/actions/runs/16845307506/job/47724057614"
      },
      {
        "check": "WARNING",
        "config": "windows-release",
        "r": "4.5.1",
        "url": "https://github.com/r-universe/r-multiverse/actions/runs/16845307506/job/47724057622"
      }
    ]
  },
  "glaredb": {
    "success": [true],
    "published": ["2025-08-22 15:45:47.186 UTC"],
    "version": ["0.0.5"],
    "remote_hash": ["ff810e8c5a1b7050d84b375b9ef33210102213f0"]
  },
  "healthyr": {
    "success": [false],
    "published": ["2025-08-08 03:38:40.168 UTC"],
    "version": ["0.0.0.9000"],
    "remote_hash": ["37a8c7844582bf6dbbc80bf960aa176e2c3e9435"],
    "r_cmd_check": [
      {
        "check": "WARNING",
        "config": "linux-release-x86_64",
        "r": "4.5.1",
        "url": "https://github.com/r-universe/r-multiverse/actions/runs/16821234649/job/47648488261"
      },
      {
        "check": "WARNING",
        "config": "macos-release-arm64",
        "r": "4.5.1",
        "url": "https://github.com/r-universe/r-multiverse/actions/runs/16821234649/job/47648488244"
      },
      {
        "check": "WARNING",
        "config": "windows-release",
        "r": "4.5.1",
        "url": "https://github.com/r-universe/r-multiverse/actions/runs/16821234649/job/47648488259"
      }
    ]
  },
  "httpgd": {
    "success": [true],
    "published": ["2025-08-08 03:46:18.937 UTC"],
    "version": ["2.0.4"],
    "remote_hash": ["dd6ed3a687a2d7327bb28ca46725a0a203eb2a19"]
  },
  "ichimoku": {
    "success": [true],
    "published": ["2025-08-19 10:00:25.108 UTC"],
    "version": ["1.5.6"],
    "remote_hash": ["43f02878819ca3a868cfa74513117b9dfc141755"]
  },
  "igraph": {
    "success": [true],
    "published": ["2025-08-03 07:43:10.582 UTC"],
    "version": ["2.1.4"],
    "remote_hash": ["affdf8c714ace2e3b66dbcaee24ca2211633f964"]
  },
  "IMD": {
    "success": [false],
    "published": ["2025-08-04 04:37:15.838 UTC"],
    "version": ["1.2.1"],
    "remote_hash": ["8cc26c4f70bf6e07c47bab089c7bad18c864223c"],
    "cran": ["1.2.2"]
  },
  "jagstargets": {
    "success": [true],
    "published": ["2025-08-14 03:56:41.604 UTC"],
    "version": ["1.2.3"],
    "remote_hash": ["fef92d0d74f6e9832459ce4bee69396bca21fd3f"]
  },
  "later": {
    "success": [true],
    "published": ["2025-08-27 09:34:05.927 UTC"],
    "version": ["1.4.4"],
    "remote_hash": ["e0a848e766bcdc228631129937e60a24265b4950"]
  },
  "litedown": {
    "success": [true],
    "published": ["2025-08-08 03:37:28.658 UTC"],
    "version": ["0.7"],
    "remote_hash": ["637bdf024a413116174f09c25f7d366c4bd43a94"]
  },
  "loneliness": {
    "success": [false],
    "published": ["2025-08-29 03:45:11.237 UTC"],
    "version": ["0.0.0.9000"],
    "remote_hash": ["330d200bf9de4a76ca1e82e3d84a3c5aba946707"],
    "r_cmd_check": [
      {
        "check": "WARNING",
        "config": "linux-release-x86_64",
        "r": "4.5.1",
        "url": "https://github.com/r-universe/r-multiverse/actions/runs/17314004125/job/49153610415"
      },
      {
        "check": "WARNING",
        "config": "macos-release-arm64",
        "r": "4.5.1",
        "url": "https://github.com/r-universe/r-multiverse/actions/runs/17314004125/job/49153610403"
      },
      {
        "check": "WARNING",
        "config": "windows-release",
        "r": "4.5.1",
        "url": "https://github.com/r-universe/r-multiverse/actions/runs/17314004125/job/49153610408"
      }
    ]
  },
  "milRex": {
    "success": [true],
    "published": ["2025-08-09 03:38:48.065 UTC"],
    "version": ["1.1.0"],
    "remote_hash": ["3a8c6096b0e162445f119fc2dfc46ff41d0089ba"]
  },
  "mirai": {
    "success": [true],
    "published": ["2025-08-19 09:56:33.081 UTC"],
    "version": ["2.4.1"],
    "remote_hash": ["170d0216836878ea501710046f0859b9b33006f2"]
  },
  "multitools": {
    "success": [true],
    "published": ["2025-08-05 06:03:01.431 UTC"],
    "version": ["0.1.1"],
    "remote_hash": ["c73b933868d8c6884df4220c25779cd0874ec7de"]
  },
  "multiverse.internals": {
    "success": [true],
    "published": ["2025-08-31 02:50:50.357 UTC"],
    "version": ["1.1.1"],
    "remote_hash": ["e8e5a794360444658db6de4a59077eced2940304"]
  },
  "nanoarrow": {
    "success": [true],
    "published": ["2025-08-02 07:32:24.292 UTC"],
    "version": ["0.7.0"],
    "remote_hash": ["2cfba631b40886f1418a463f3b7c4552c8ae0dc7"]
  },
  "nanonext": {
    "success": [true],
    "published": ["2025-08-13 07:12:59.845 UTC"],
    "version": ["1.6.2"],
    "remote_hash": ["68eb478e6151f2fd72e3c397edfd98bdd6768be8"]
  },
  "polars": {
    "success": [true],
    "published": ["2025-08-22 14:22:57.563 UTC"],
    "version": ["1.2.1"],
    "remote_hash": ["55feebecf0fdbff0e493ead74bd01551cf4f6806"]
  },
  "polars0": {
    "success": [true],
    "published": ["2025-08-12 04:37:37.084 UTC"],
    "version": ["1.0.0"],
    "remote_hash": ["8972f0106e87e1f02da005613855fe99628d66db"]
  },
  "prophet": {
    "success": [false],
    "published": ["2025-08-28 06:36:49.802 UTC"],
    "version": ["1.1.6"],
    "remote_hash": ["a0d1ddf27572ae9e16d6ecac1e5c485a9f9aabe2"],
    "versions": {
      "version_current": ["1.1.6"],
      "hash_current": ["a0d1ddf27572ae9e16d6ecac1e5c485a9f9aabe2"],
      "version_highest": ["1.1.6"],
      "hash_highest": ["6e9fa67985b34a97bc98a40520ac6072d8d60491"]
    }
  },
  "prqlr": {
    "success": [true],
    "published": ["2025-08-04 03:56:51.108 UTC"],
    "version": ["0.10.1"],
    "remote_hash": ["85d9fa32cf35a189942953a873a5351b1fae2516"]
  },
  "rJavaEnv": {
    "success": [true],
    "published": ["2025-08-30 04:09:35.703 UTC"],
    "version": ["0.3.0"],
    "remote_hash": ["cce4a2bb65d891c3e9ba0194a67451de87a2a3ae"]
  },
  "rlang": {
    "success": [true],
    "published": ["2025-08-03 04:12:29.438 UTC"],
    "version": ["1.1.6"],
    "remote_hash": ["830745e8798b7f2ef7c4afd96ed40d4adfe2fdf0"]
  },
  "Rvision": {
    "success": [false],
    "published": ["2025-08-25 03:01:42.095 UTC"],
    "version": ["0.8.0"],
    "remote_hash": ["972627f8aac8a0eb95f8b166e316cb9b0ee5930c"],
    "license": ["NOT FOUND"],
    "r_cmd_check": [
      {
        "check": "ERROR",
        "config": "source",
        "r": "4.5.1",
        "url": "https://github.com/r-universe/r-multiverse/actions/runs/17160253097/job/48782760234"
      }
    ]
  },
  "rwasm": {
    "success": [true],
    "published": ["2025-08-13 10:30:47.957 UTC"],
    "version": ["0.3.0"],
    "remote_hash": ["005588296e03080357c7140c1eaf8b47ccabe0bc"]
  },
  "SBC": {
    "success": [false],
    "published": ["2025-08-29 05:51:32.361 UTC"],
    "version": ["0.3.0.9000"],
    "remote_hash": ["9ddc803105f5350dae6efb4ae2657e89d2a54aa8"],
    "r_cmd_check": [
      {
        "check": "WARNING",
        "config": "linux-release-x86_64",
        "r": "4.5.1",
        "url": "https://github.com/r-universe/r-multiverse/actions/runs/17315073432/job/49158296485"
      },
      {
        "check": "WARNING",
        "config": "macos-release-arm64",
        "r": "4.5.1",
        "url": "https://github.com/r-universe/r-multiverse/actions/runs/17315073432/job/49158296494"
      },
      {
        "check": "ERROR",
        "config": "source",
        "r": "4.5.1",
        "url": "https://github.com/r-universe/r-multiverse/actions/runs/17315073432/job/49156411769"
      },
      {
        "check": "WARNING",
        "config": "windows-release",
        "r": "4.5.1",
        "url": "https://github.com/r-universe/r-multiverse/actions/runs/17315073432/job/49158296512"
      }
    ]
  },
  "stantargets": {
    "success": [false],
    "published": ["2025-08-27 03:38:50.355 UTC"],
    "version": ["0.1.2"],
    "remote_hash": ["638326106594be70c5f851c767349e4192740771"],
    "r_cmd_check": [
      {
        "check": "WARNING",
        "config": "linux-release-x86_64",
        "r": "4.5.1",
        "url": "https://github.com/r-universe/r-multiverse/actions/runs/17256522229/job/48969736325"
      },
      {
        "check": "WARNING",
        "config": "macos-release-arm64",
        "r": "4.5.1",
        "url": "https://github.com/r-universe/r-multiverse/actions/runs/17256522229/job/48969736314"
      },
      {
        "check": "ERROR",
        "config": "source",
        "r": "4.5.1",
        "url": "https://github.com/r-universe/r-multiverse/actions/runs/17256522229/job/48969538264"
      },
      {
        "check": "WARNING",
        "config": "windows-release",
        "r": "4.5.1",
        "url": "https://github.com/r-universe/r-multiverse/actions/runs/17256522229/job/48969736315"
      }
    ],
    "remotes": ["hyunjimoon/SBC", "stan-dev/cmdstanr"]
  },
  "string2path": {
    "success": [true],
    "published": ["2025-08-24 06:16:57.713 UTC"],
    "version": ["0.2.2"],
    "remote_hash": ["64be930c5bbef7e1cc491ccc52c115991113d2ac"]
  },
  "tarchetypes": {
    "success": [true],
    "published": ["2025-08-08 04:08:06.250 UTC"],
    "version": ["0.13.1"],
    "remote_hash": ["ef15320481cfa9cce782237153aad38eac31a3b2"]
  },
  "targets": {
    "success": [true],
    "published": ["2025-08-27 05:29:57.611 UTC"],
    "version": ["1.11.3"],
    "remote_hash": ["38e43681e0d5c8a589b41fdc80807d432ec4eb74"]
  },
  "targetsketch": {
    "success": [true],
    "published": ["2025-08-04 04:08:06.698 UTC"],
    "version": ["0.0.1"],
    "remote_hash": ["a199a734b16f91726698a19e5f147f57f79cb2b6"]
  },
  "taxizedb": {
    "success": [false],
    "published": ["2025-08-03 07:49:24.647 UTC"],
    "version": ["0.3.1"],
    "remote_hash": ["5732f9777142cd0034b64d5ae8b9aea0605cfaab"],
    "cran": ["0.3.2"]
  },
  "tidypolars": {
    "success": [true],
    "published": ["2025-08-16 09:58:57.078 UTC"],
    "version": ["0.14.1"],
    "remote_hash": ["5acc4a512a1d81cf3187ff14f4718f55d2105b44"]
  },
  "tidytensor": {
    "success": [false],
    "published": ["2025-08-20 03:06:04.937 UTC"],
    "version": ["1.0.0"],
    "remote_hash": ["14f5b87d2dfae20eb35cfd974adf660a4fd89980"],
    "r_cmd_check": [
      {
        "check": "WARNING",
        "config": "linux-release-x86_64",
        "r": "4.5.1",
        "url": "https://github.com/r-universe/r-multiverse/actions/runs/17087298222/job/48453943392"
      },
      {
        "check": "WARNING",
        "config": "macos-release-arm64",
        "r": "4.5.1",
        "url": "https://github.com/r-universe/r-multiverse/actions/runs/17087298222/job/48453943417"
      },
      {
        "check": "ERROR",
        "config": "source",
        "r": "4.5.1",
        "url": "https://github.com/r-universe/r-multiverse/actions/runs/17087298222/job/48453790985"
      },
      {
        "check": "WARNING",
        "config": "windows-release",
        "r": "4.5.1",
        "url": "https://github.com/r-universe/r-multiverse/actions/runs/17087298222/job/48453943425"
      }
    ]
  },
  "unigd": {
    "success": [true],
    "published": ["2025-08-04 06:03:53.973 UTC"],
    "version": ["0.1.3"],
    "remote_hash": ["b6c5181aa1c7c0888b923663b7fe903c6759d86d"]
  },
  "webchem": {
    "success": [true],
    "published": ["2025-08-16 06:03:17.588 UTC"],
    "version": ["1.3.1"],
    "remote_hash": ["2131a4e718996f16467be458fd7378116523414d"]
  },
  "webseq": {
    "success": [false],
    "published": ["2025-08-30 04:00:44.311 UTC"],
    "version": ["0.1"],
    "remote_hash": ["b710f93da5b8dd8a30fa170cdf3da8da943fbae1"],
    "r_cmd_check": [
      {
        "check": "WARNING",
        "config": "linux-release-x86_64",
        "r": "4.5.1",
        "url": "https://github.com/r-universe/r-multiverse/actions/runs/17339056751/job/49230391373"
      },
      {
        "check": "WARNING",
        "config": "macos-release-arm64",
        "r": "4.5.1",
        "url": "https://github.com/r-universe/r-multiverse/actions/runs/17339056751/job/49230391352"
      },
      {
        "check": "WARNING",
        "config": "windows-release",
        "r": "4.5.1",
        "url": "https://github.com/r-universe/r-multiverse/actions/runs/17339056751/job/49230391335"
      }
    ]
  },
  "wildfires": {
    "success": [false],
    "published": ["2025-08-16 03:22:34.802 UTC"],
    "version": ["0.9.0"],
    "remote_hash": ["228c24be602b16073ff2bc8096d5df9d42dc6ea1"],
    "r_cmd_check": [
      {
        "check": "WARNING",
        "config": "linux-release-x86_64",
        "r": "4.5.1",
        "url": "https://github.com/r-universe/r-multiverse/actions/runs/17003663891/job/48209927474"
      },
      {
        "check": "WARNING",
        "config": "macos-release-arm64",
        "r": "4.5.1",
        "url": "https://github.com/r-universe/r-multiverse/actions/runs/17003663891/job/48209927464"
      },
      {
        "check": "WARNING",
        "config": "windows-release",
        "r": "4.5.1",
        "url": "https://github.com/r-universe/r-multiverse/actions/runs/17003663891/job/48209927475"
      }
    ]
  },
  "zstdlite": {
    "success": [true],
    "published": ["2025-08-04 04:05:11.713 UTC"],
    "version": ["0.2.6"],
    "remote_hash": ["585458ccbe36eaa179d8b30f04f1e3a91dc6b993"]
  }
}
